[
  {
    "postId": 1,
    "userId": 1,
    "categoryId": 1,
    "cityId": 1,
    "postDescription": "Cras sit amet nibh libero, in gravida nulla. Nulla vel metus scelerisque ante sollicitudin commodo. Cras purus odio, vestibulum in vulputate at, tempus viverra turpis. Fusce condimentum nunc ac nisi vulputate fringilla. Donec lacinia congue felis in faucibus.",
    "statusId": true,
    "createdBy": 1,
    "createdDate": "2015-12-15 12:24:50",
    "userName": "Bhavik Patel",
    "likes": 10,
    "comments": 1,
    "favorites": 10
  },
  {
    "postId": 2,
    "userId": 1,
    "categoryId": 1,
    "cityId": 1,
    "postDescription": "Donec sed odio dui. Nullam quis risus eget urna mollis ornare vel eu leo. Cum sociis natoque penatibus et magnis dis parturient montes, nascetur ridiculus mus.",
    "statusId": true,
    "createdBy": 1,
    "createdDate": "2016-01-07 12:24:50",
    "userName": "Other User",
    "likes": 899,
    "comments": 114,
    "favorites": 5
  },
  {
    "postId": 3,
    "userId": 1,
    "categoryId": 2,
    "cityId": 1,
    "postDescription": "Cras sit amet nibh libero, in gravida nulla. Nulla vel metus scelerisque ante sollicitudin commodo. Cras purus odio, vestibulum in vulputate at, tempus viverra turpis. Fusce condimentum nunc ac nisi vulputate fringilla. Donec lacinia congue felis in faucibus.",
    "statusId": false,
    "createdBy": 1,
    "createdDate": "2015-01-07 12:24:50",
    "userName": "Another User Name",
    "likes": 54,
    "comments": 12,
    "favorites": 3
  },
  {
    "postId": 4,
    "userId": 1,
    "categoryId": 2,
    "cityId": 1,
    "postDescription": "Donec sed odio dui. Nullam quis risus eget urna mollis ornare vel eu leo. Cum sociis natoque penatibus et magnis dis parturient montes, nascetur ridiculus mus.",
    "statusId": true,
    "createdBy": 1,
    "createdDate": "2016-01-04 12:24:50",
    "userName": "My User Name",
    "likes": 89,
    "comments": 2,
    "favorites": 20
  },
  {
    "postId": 5,
    "userId": 1,
    "categoryId": 1,
    "cityId": 2,
    "postDescription": "Donec sed odio dui. Nullam quis risus eget urna mollis ornare vel eu leo. Cum sociis natoque penatibus et magnis dis parturient montes, nascetur ridiculus mus.",
    "statusId": false,
    "createdBy": 1,
    "createdDate": "2015-12-05 12:24:50",
    "userName": "Bhavik Patel",
    "likes": 96,
    "comments": 14,
    "favorites": 9
  },
  {
    "postId": 6,
    "userId": 1,
    "categoryId": 2,
    "cityId": 2,
    "postDescription": "Cras sit amet nibh libero, in gravida nulla. Nulla vel metus scelerisque ante sollicitudin commodo. Cras purus odio, vestibulum in vulputate at, tempus viverra turpis. Fusce condimentum nunc ac nisi vulputate fringilla. Donec lacinia congue felis in faucibus.",
    "statusId": true,
    "createdBy": 1,
    "createdDate": "2015-10-05 20:24:50",
    "userName": "Third User Name",
    "likes": 55,
    "comments": 0,
    "favorites": 0
  },
  {
    "postId": 7,
    "userId": 1,
    "categoryId": 3,
    "cityId": 1,
    "postDescription": "Cras sit amet nibh libero, in gravida nulla. Nulla vel metus scelerisque ante sollicitudin commodo. Cras purus odio, vestibulum in vulputate at, tempus viverra turpis. Fusce condimentum nunc ac nisi vulputate fringilla. Donec lacinia congue felis in faucibus.",
    "statusId": true,
    "createdBy": 1,
    "createdDate": "2015-09-09 23:24:50",
    "userName": "New User Name",
    "likes": 0,
    "comments": 1,
    "favorites": 0
  }
]